[
{
    "id": "111",
    "name": "父节点1",
    "code": "1111",
    "children": [
    {
        "id": "12",
        "name": "子节点11",
        "code": "11111",
        "children": [
        {
            "id": "13",
            "name": "子节点12",
            "code": "111"
        },
        {
            "id": "24",
            "name": "子节点23",
            "code": "111"
        },
        {
            "id": "35",
            "name": "子节点34",
            "code": "11"
        }]
    },
    {
        "id": "2",
        "name": "子节点2",
        "code": "1"
    },
    {
        "id": "3",
        "name": "子节点3",
        "code": "111"
    }]
}]